keydive/__init__.py
keydive/__main__.py
keydive/adb/__init__.py
keydive/adb/remote.py
keydive/adb/vendor.py
keydive/core.py
keydive/drm/__init__.py
keydive/drm/cdm.py
keydive/drm/device.py
keydive/drm/keybox.py
keydive/drm/modules/__init__.py
keydive/drm/modules/client.py
keydive/drm/modules/oemcrypto.py
keydive/drm/modules/provisioning.py
keydive/drm/protocol/license_pb2.py
keydive/drm/protocol/license_pb2.pyi
keydive/keydive.js
keydive/utils.py
keydive-3.0.5.dist-info/entry_points.txt
keydive-3.0.5.dist-info/LICENSE.txt
keydive-3.0.5.dist-info/METADATA
keydive-3.0.5.dist-info/WHEEL
keydive-3.0.5.dist-info/RECORD
