Metadata-Version: 2.1
Name: keydive
Version: 3.0.5
Summary: Extract Widevine L3 keys from Android devices effortlessly, spanning multiple Android versions for DRM research and education.
Home-page: https://github.com/hyugogirubato/KeyDive
License: MIT
Keywords: python,drm,widevine,google
Author: hyugogirubato
Author-email: 65763543+hyugogirubato@users.noreply.github.com
Requires-Python: >=3.8,<4.0
Classifier: Development Status :: 5 - Production/Stable
Classifier: Intended Audience :: Developers
Classifier: Intended Audience :: End Users/Desktop
Classifier: License :: OSI Approved :: MIT License
Classifier: Natural Language :: English
Classifier: Operating System :: OS Independent
Classifier: Programming Language :: Python :: 3
Classifier: Programming Language :: Python :: 3.8
Classifier: Programming Language :: Python :: 3.9
Classifier: Programming Language :: Python :: 3.10
Classifier: Programming Language :: Python :: 3.11
Classifier: Programming Language :: Python :: 3.12
Classifier: Topic :: Multimedia :: Video
Classifier: Topic :: Security :: Cryptography
Classifier: Topic :: Software Development :: Libraries :: Python Modules
Provides-Extra: offline
Requires-Dist: Flask (>=3.0.3) ; extra == "offline"
Requires-Dist: Unidecode (>=1.4.0)
Requires-Dist: asn1crypto (>=1.5.1)
Requires-Dist: coloredlogs (>=15.0.1)
Requires-Dist: construct (>=2.10.70,<3.0.0)
Requires-Dist: crccheck (>=1.3.0)
Requires-Dist: cryptography (>=43.0.3)
Requires-Dist: frida (>=17.1.3)
Requires-Dist: pathvalidate (>=3.2.1)
Requires-Dist: protobuf (>=5.29.5,<6.0.0)
Requires-Dist: requests (>=2.32.3)
Requires-Dist: rich-argparse (>=1.7.1)
Requires-Dist: xmltodict (>=0.14.2)
Project-URL: Changelog, https://github.com/hyugogirubato/KeyDive/blob/main/CHANGELOG.md
Project-URL: Functions, https://github.com/hyugogirubato/KeyDive/blob/main/docs/FUNCTIONS.md
Project-URL: Issues, https://github.com/hyugogirubato/KeyDive/issues
Project-URL: Packages, https://github.com/hyugogirubato/KeyDive/blob/main/docs/PACKAGE.md
Project-URL: Repository, https://github.com/hyugogirubato/KeyDive
